Workbook

Sheet SOCIOS
A1: N° | B1: Nombre completo | C1: DNI | D1: Fecha ingreso | E1: Aporte mesual | F1: Aporte | G1: estado | H1: Reunion 3/7/26
A2: 1 | B2: Filomena Valdez Curi | D2: 45658 | E2: 100 | F2: ='APORTES 2026'!AC3 -> 1800 | G2: Activo | H2: F
A3: 2 | B3: Efrain Infante Mejia | D3: 45658 | E3: 100 | F3: ='APORTES 2026'!AC4 -> 1800 | G3: Activo | H3: T
A4: 3 | B4: Estefani Corali Infante Fernández | D4: 45658 | E4: 100 | F4: ='APORTES 2026'!AC5 -> 1800 | G4: Activo | H4: T
A5: 4 | B5: Juan Carlos Cuba Sulca | D5: 45658 | E5: 100 | F5: ='APORTES 2026'!AC6 -> 1800 | G5: Activo | H5: P
A6: 5 | B6: Julio Cesar Fernandez Valdez | D6: 45658 | E6: 100 | F6: ='APORTES 2026'!AC7 -> 1800 | G6: Activo | H6: F
A7: 6 | B7: Mariela Fernández Valdez | D7: 45658 | E7: 100 | F7: ='APORTES 2026'!AC8 -> 1800 | G7: Activo | H7: T
A8: 7 | B8: Michael Fernández Valdez | D8: 45658 | E8: 100 | F8: ='APORTES 2026'!AC9 -> 1800 | G8: Activo | H8: P
A9: 8 | B9: Paul Jimmy Auccapuclla Barrientos | C9: 70428001 | D9: 45658 | E9: 100 | F9: ='APORTES 2026'!AC10 -> 1800 | G9: Activo | H9: P
A10: 9 | B10: Saul Godoy Mallqui | D10: 45658 | E10: 100 | F10: ='APORTES 2026'!AC11 -> 1800 | G10: Activo | H10: Permiso
A11: 10 | B11: Sayda Quispe Curi | D11: 45658 | E11: 100 | F11: ='APORTES 2026'!AC12 -> 1800 | G11: Activo | H11: P
A12: 11 | B12: Yeli Melusca Algoner Mejia | D12: 45658 | E12: 100 | F12: ='APORTES 2026'!AC13 -> 1800 | G12: Activo | H12: F
A13: 12 | B13: Yésica Godoy Mallqui | D13: 45658 | E13: 100 | F13: ='APORTES 2026'!AC14 -> 1800 | G13: Activo | H13: P
A14: 13 | B14: Maribel Cayllahua Sulcacondor | D14: 46023 | E14: 100 | F14: ='APORTES 2026'!AC15 -> 700 | G14: Activo | H14: P
A15: 14 | B15: Jose Luis Fernandez Pariona | D15: 46023 | E15: 100 | F15: ='APORTES 2026'!AC16 -> 700 | G15: Activo | H15: P
A16: 15 | B16: Brith Zarella Roca Godoy | D16: 45658 | E16: 100 | F16: ='APORTES 2026'!AC17 -> 705 | G16: Activo | H16: P
A17: 16 | B17: Jeferson Mendoza Quispe | D17: 46204 | E17: 100 | F17: ='APORTES 2026'!AC18 -> 100 | G17: Activo
A18: 17 | D18: 45658
A19: 18 | D19: 45658
A20: 19 | D20: 45658
A21: 20 | D21: 45658
A22: 21 | D22: 45658
A23: 22 | D23: 45658
A24: 23 | D24: 45658
A25: 24 | D25: 45658
A26: 25 | D26: 45658
A27: 26 | B27: Banquito Sumac Ayllu | D27: 45658

Sheet RESUMEN 
E1: Socios | G1: Banquito | K1: Total movimiento
A2: Año | B2: Mes | C2: Socio | D2: Movimiento | E2: Aporte | F2: Acumulado | G2: Aporte | H2: Inversion | I2: Salida | J2: Saldo
A3: 2025 | B3: Febrero | C3: Banquito | D3: Entrada | E3: ='APORTES 2025'!D27 -> 1200 | F3: =E3 -> 1200 | G3: =E3 -> 1200 | H3: 0 | I3: 0 | J3: =G3+H3-I3 -> 1200
B4: Marzo | C4: Banquito | D4: Entrada | E4: ='APORTES 2025'!E27 -> 1200 | F4: =E4+F3 -> 2400 | G4: =E4 -> 1200 | H4: 0 | I4: 0 | J4: =J3+G4+H4-I4 -> 2400
B5: Abril | C5: Banquito | D5: Entrada | E5: ='APORTES 2025'!F27 -> 1200 | F5: =E5+F4 -> 3600 | G5: =E5 -> 1200 | H5: 0 | I5: 0 | J5: =J4+G5+H5-I5 -> 3600
B6: Mayo | C6: Banquito | D6: Entrada | E6: ='APORTES 2025'!G27 -> 1200 | F6: =E6+F5 -> 4800 | G6: =E6 -> 1200 | H6: 0 | I6: 0 | J6: =J5+G6+H6-I6 -> 4800
B7: Junio | C7: Banquito | D7: Salida | E7: ='APORTES 2025'!H27 -> 1200 | F7: =E7+F6 -> 6000 | G7: =E7 -> 1200 | H7: 0 | I7: 4800 | J7: =J6+G7+H7-I7 -> 1200
B8: Julio | C8: Banquito | D8: Entrada | E8: ='APORTES 2025'!I27 -> 1200 | F8: =E8+F7 -> 7200 | G8: =E8 -> 1200 | H8: 0 | I8: 0 | J8: =J7+G8+H8-I8 -> 2400
B9: Agosto | C9: Banquito | D9: Entrada | E9: ='APORTES 2025'!J27 -> 1200 | F9: =E9+F8 -> 8400 | G9: =E9 -> 1200 | H9: =4800+430.1 -> 5230.1 | I9: 0 | J9: =J8+G9+H9-I9 -> 8830.1
B10: Septiembre | C10: Banquito | D10: Entrada | E10: ='APORTES 2025'!K27 -> 1200 | F10: =E10+F9 -> 9600 | G10: =E10 -> 1200 | H10: 0 | I10: 0 | J10: =J9+G10+H10-I10 -> 10030.1
B11: Octubre | C11: Banquito | D11: Entrada | E11: ='APORTES 2025'!L27 -> 1200 | F11: =E11+F10 -> 10800 | G11: =E11 -> 1200 | H11: 0 | I11: 0 | J11: =J10+G11+H11-I11 -> 11230.1
B12: Noviembre | C12: Banquito | D12: Entrada | E12: ='APORTES 2025'!M27 -> 1200 | F12: =E12+F11 -> 12000 | G12: =E12 -> 1200 | H12: 0 | I12: 0 | J12: =J11+G12+H12-I12 -> 12430.1
B13: Diciembre | C13: Banquito | D13: Entrada | E13: ='APORTES 2025'!N27 -> 1200 | F13: =E13+F12 -> 13200 | G13: =E13 -> 1200 | H13: 0 | I13: 12200 | J13: =J12+G13+H13-I13 -> 1430.1 | K13: =I13+J13 -> 13630.1
A14: 2026 | B14: Enero | C14: Banquito | D14: Entrada | E14: ='APORTES 2026'!D28 -> 1500 | F14: =E14+F13 -> 14700 | G14: =E14+'APORTES 2026'!E28 -> 1555 | J14: =J13+G14+H14-I14 -> 2985.1
B15: Febrero | C15: Banquito | D15: Entrada | E15: ='APORTES 2026'!F28 -> 1500 | F15: =E15+F14 -> 16200 | G15: =E15+'APORTES 2026'!G28 -> 1515 | J15: =J14+G15+H15-I15 -> 4500.1
B16: Marzo | C16: Banquito | D16: Entrada | E16: ='APORTES 2026'!H28 -> 1505 | F16: =E16+F15 -> 17705 | G16: =E16+'APORTES 2026'!I28 -> 1520 | H16: =12200+1267.57 -> 13467.57 | J16: =J15+G16+H16-I16 -> 19487.67 | K16: =1267.57+430 -> 1697.57
B17: Abril | C17: Banquito | D17: Entrada | E17: ='APORTES 2026'!J28 -> 1500 | F17: =E17+F16 -> 19205 | G17: =E17+'APORTES 2026'!K28 -> 1505 | J17: =J16+G17+H17-I17 -> 20992.67
B18: Mayo | C18: Banquito | D18: Entrada | E18: ='APORTES 2026'!L29 -> 1500 | F18: =E18+F17 -> 20705 | G18: =E18 -> 1500 | J18: =J17+G18+H18-I18 -> 22492.67
B19: Junio | C19: Banquito | D19: Entrada | E19: ='APORTES 2026'!N28 -> 1500 | F19: =E19+F18 -> 22205 | G19: =E19+'APORTES 2026'!O28 -> 1520 | J19: =J18+G19+H19-I19 -> 24012.67 | L19: 24013.82
B20: Julio | C20: Banquito | D20: Entrada | E20: ='APORTES 2026'!P28 -> 1600 | F20: =E20+F19 -> 23805 | G20: =E20+'APORTES 2026'!Q28 -> 1605 | J20: =J19+G20+H20-I20 -> 25617.67
B21: Agosto | C21: Banquito | D21: Entrada | F21: =E21+F20 -> 23805 | J21: =J20+G21+H21-I21 -> 25617.67
B22: Setiembre | C22: Banquito | D22: Entrada | F22: =E22+F21 -> 23805 | J22: =J21+G22+H22-I22 -> 25617.67
B23: Octubre | C23: Banquito | D23: Entrada | F23: =E23+F22 -> 23805 | J23: =J22+G23+H23-I23 -> 25617.67
B24: Noviembre | C24: Banquito | D24: Entrada | F24: =E24+F23 -> 23805 | J24: =J23+G24+H24-I24 -> 25617.67
B25: Diciembre | C25: Banquito | D25: Entrada | F25: =E25+F24 -> 23805 | J25: =J24+G25+H25-I25 -> 25617.67
J26: =J25+G26-I26 -> 25617.67
J27: =J26+G27-I27 -> 25617.67
J28: =J27+G28-I28 -> 25617.67
J29: =J28+G29-I29 -> 25617.67
J30: =J29+G30-I30 -> 25617.67

Sheet APORTES 2026
A1: N° | B1: Socio | C1: Saldo inicial | D1: ENE | F1: FEB | H1: MAR | J1: ABR | L1: MAY | N1: JUN | P1: JUL | R1: AGO | T1: SEP | V1: OCT | X1: NOV | Z1: DIC | AB1: Total 2026 | AC1: Total 2025+2026
D2: Aporte | E2: Mora | F2: Aporte | G2: Mora | H2: Aporte | I2: Mora | J2: Aporte | K2: Mora | L2: Aporte | M2: Mora | N2: Aporte | O2: Mora | P2: Aporte | Q2: Mora | R2: Aporte | S2: Mora | T2: Aporte | U2: Mora | V2: aporte | W2: Mora | X2: Aporte | Y2: Mora | Z2: Aporte | AA2: Mora
A3: =SOCIOS!A2 -> 1 | B3: =SOCIOS!B2 -> Filomena Valdez Curi | C3: ='APORTES 2025'!O2 -> 1100 | D3: 100 | F3: 100 | G3: 5 | H3: 100 | J3: 100 | L3: 100 | N3: 100 | O3: 5 | P3: 100 | R3: 0 | T3: 0 | V3: 0 | X3: 0 | Z3: 0 | AB3: =D3+F3+H3+J3+L3+N3+P3+R3+T3+V3+X3+Z3 -> 700 | AC3: =C3+AB3 -> 1800
A4: =SOCIOS!A3 -> 2 | B4: =SOCIOS!B3 -> Efrain Infante Mejia | C4: ='APORTES 2025'!O3 -> 1100 | D4: 100 | F4: 100 | H4: 100 | J4: 100 | L4: 100 | N4: 100 | O4: 5 | P4: 100 | R4: 0 | T4: 0 | V4: 0 | X4: 0 | Z4: 0 | AB4: =D4+F4+H4+J4+L4+N4+P4+R4+T4+V4+X4+Z4 -> 700 | AC4: =C4+AB4 -> 1800
A5: =SOCIOS!A4 -> 3 | B5: =SOCIOS!B4 -> Estefani Corali Infante Fernández | C5: ='APORTES 2025'!O4 -> 1100 | D5: 100 | F5: 100 | H5: 100 | J5: 100 | L5: 100 | N5: 100 | O5: 5 | P5: 100 | R5: 0 | T5: 0 | V5: 0 | X5: 0 | Z5: 0 | AB5: =D5+F5+H5+J5+L5+N5+P5+R5+T5+V5+X5+Z5 -> 700 | AC5: =C5+AB5 -> 1800
A6: =SOCIOS!A5 -> 4 | B6: =SOCIOS!B5 -> Juan Carlos Cuba Sulca | C6: ='APORTES 2025'!O5 -> 1100 | D6: 100 | E6: 5 | F6: 100 | G6: 5 | H6: 100 | I6: 5 | J6: 100 | K6: 5 | L6: 100 | N6: 100 | P6: 100 | R6: 0 | T6: 0 | V6: 0 | X6: 0 | Z6: 0 | AB6: =D6+F6+H6+J6+L6+N6+P6+R6+T6+V6+X6+Z6 -> 700 | AC6: =C6+AB6 -> 1800
A7: =SOCIOS!A6 -> 5 | B7: =SOCIOS!B6 -> Julio Cesar Fernandez Valdez | C7: ='APORTES 2025'!O6 -> 1100 | D7: 100 | E7: 5 | F7: 100 | H7: 100 | J7: 100 | L7: 100 | N7: 100 | P7: 100 | R7: 0 | T7: 0 | V7: 0 | X7: 0 | Z7: 0 | AB7: =D7+F7+H7+J7+L7+N7+P7+R7+T7+V7+X7+Z7 -> 700 | AC7: =C7+AB7 -> 1800
A8: =SOCIOS!A7 -> 6 | B8: =SOCIOS!B7 -> Mariela Fernández Valdez | C8: ='APORTES 2025'!O7 -> 1100 | D8: 100 | F8: 100 | H8: 100 | J8: 100 | L8: 100 | N8: 100 | O8: 5 | P8: 100 | R8: 0 | T8: 0 | V8: 0 | X8: 0 | Z8: 0 | AB8: =D8+F8+H8+J8+L8+N8+P8+R8+T8+V8+X8+Z8 -> 700 | AC8: =C8+AB8 -> 1800
A9: =SOCIOS!A8 -> 7 | B9: =SOCIOS!B8 -> Michael Fernández Valdez | C9: ='APORTES 2025'!O8 -> 1100 | D9: 100 | E9: 5 | F9: 100 | H9: 100 | J9: 100 | L9: 100 | N9: 100 | P9: 100 | R9: 0 | T9: 0 | V9: 0 | X9: 0 | Z9: 0 | AB9: =D9+F9+H9+J9+L9+N9+P9+R9+T9+V9+X9+Z9 -> 700 | AC9: =C9+AB9 -> 1800
A10: =SOCIOS!A9 -> 8 | B10: =SOCIOS!B9 -> Paul Jimmy Auccapuclla Barrientos | C10: ='APORTES 2025'!O9 -> 1100 | D10: 100 | E10: 5 | F10: 100 | H10: 100 | J10: 100 | L10: 100 | N10: 100 | P10: 100 | R10: 0 | T10: 0 | V10: 0 | X10: 0 | Z10: 0 | AB10: =D10+F10+H10+J10+L10+N10+P10+R10+T10+V10+X10+Z10 -> 700 | AC10: =C10+AB10 -> 1800
A11: =SOCIOS!A10 -> 9 | B11: =SOCIOS!B10 -> Saul Godoy Mallqui | C11: ='APORTES 2025'!O10 -> 1100 | D11: 100 | E11: 5 | F11: 100 | H11: 100 | I11: 5 | J11: 100 | L11: 100 | N11: 100 | P11: 100 | R11: 0 | T11: 0 | V11: 0 | X11: 0 | Z11: 0 | AB11: =D11+F11+H11+J11+L11+N11+P11+R11+T11+V11+X11+Z11 -> 700 | AC11: =C11+AB11 -> 1800
A12: =SOCIOS!A11 -> 10 | B12: =SOCIOS!B11 -> Sayda Quispe Curi | C12: ='APORTES 2025'!O11 -> 1100 | D12: 100 | E12: 5 | F12: 100 | G12: 5 | H12: 100 | J12: 100 | L12: 100 | N12: 100 | P12: 100 | R12: 0 | T12: 0 | V12: 0 | X12: 0 | Z12: 0 | AB12: =D12+F12+H12+J12+L12+N12+P12+R12+T12+V12+X12+Z12 -> 700 | AC12: =C12+AB12 -> 1800
A13: =SOCIOS!A12 -> 11 | B13: =SOCIOS!B12 -> Yeli Melusca Algoner Mejia | C13: ='APORTES 2025'!O12 -> 1100 | D13: 100 | E13: 5 | F13: 100 | H13: 100 | J13: 100 | L13: 100 | N13: 100 | P13: 100 | R13: 0 | T13: 0 | V13: 0 | X13: 0 | Z13: 0 | AB13: =D13+F13+H13+J13+L13+N13+P13+R13+T13+V13+X13+Z13 -> 700 | AC13: =C13+AB13 -> 1800
A14: =SOCIOS!A13 -> 12 | B14: =SOCIOS!B13 -> Yésica Godoy Mallqui | C14: ='APORTES 2025'!O13 -> 1100 | D14: 100 | E14: 5 | F14: 100 | H14: 100 | J14: 100 | L14: 100 | N14: 100 | P14: 100 | R14: 0 | T14: 0 | V14: 0 | X14: 0 | Z14: 0 | AB14: =D14+F14+H14+J14+L14+N14+P14+R14+T14+V14+X14+Z14 -> 700 | AC14: =C14+AB14 -> 1800
A15: =SOCIOS!A14 -> 13 | B15: =SOCIOS!B14 -> Maribel Cayllahua Sulcacondor | C15: ='APORTES 2025'!O14 -> 0 | D15: 100 | F15: 100 | H15: 100 | I15: 5 | J15: 100 | L15: 100 | N15: 100 | P15: 100 | R15: 0 | T15: 0 | V15: 0 | X15: 0 | Z15: 0 | AB15: =D15+F15+H15+J15+L15+N15+P15+R15+T15+V15+X15+Z15 -> 700 | AC15: =C15+AB15 -> 700
A16: =SOCIOS!A15 -> 14 | B16: =SOCIOS!B15 -> Jose Luis Fernandez Pariona | C16: ='APORTES 2025'!O15 -> 0 | D16: 100 | E16: 10 | F16: 100 | H16: 100 | J16: 100 | L16: 100 | N16: 100 | P16: 100 | R16: 0 | T16: 0 | V16: 0 | X16: 0 | Z16: 0 | AB16: =D16+F16+H16+J16+L16+N16+P16+R16+T16+V16+X16+Z16 -> 700 | AC16: =C16+AB16 -> 700
A17: =SOCIOS!A16 -> 15 | B17: =SOCIOS!B16 -> Brith Zarella Roca Godoy | C17: ='APORTES 2025'!O16 -> 0 | D17: 100 | E17: 5 | F17: 100 | H17: 105 | J17: 100 | L17: 100 | N17: 100 | P17: 100 | R17: 0 | T17: 0 | V17: 0 | X17: 0 | Z17: 0 | AB17: =D17+F17+H17+J17+L17+N17+P17+R17+T17+V17+X17+Z17 -> 705 | AC17: =C17+AB17 -> 705
A18: =SOCIOS!A17 -> 16 | B18: =SOCIOS!B17 -> Jeferson Mendoza Quispe | C18: ='APORTES 2025'!O17 -> 0 | P18: 100 | Q18: 5 | AB18: =D18+F18+H18+J18+L18+N18+P18+R18+T18+V18+X18+Z18 -> 100 | AC18: =C18+AB18 -> 100
A19: =SOCIOS!A18 -> 17 | B19: =SOCIOS!B18 -> 0 | C19: ='APORTES 2025'!O18 -> 0 | AB19: =D19+F19+H19+J19+L19+N19+P19+R19+T19+V19+X19+Z19 -> 0 | AC19: =C19+AB19 -> 0
A20: =SOCIOS!A19 -> 18 | B20: =SOCIOS!B19 -> 0 | C20: ='APORTES 2025'!O19 -> 0 | AB20: =D20+F20+H20+J20+L20+N20+P20+R20+T20+V20+X20+Z20 -> 0 | AC20: =C20+AB20 -> 0
A21: =SOCIOS!A20 -> 19 | B21: =SOCIOS!B20 -> 0 | C21: ='APORTES 2025'!O20 -> 0 | AB21: =D21+F21+H21+J21+L21+N21+P21+R21+T21+V21+X21+Z21 -> 0 | AC21: =C21+AB21 -> 0
A22: =SOCIOS!A21 -> 20 | B22: =SOCIOS!B21 -> 0 | C22: ='APORTES 2025'!O21 -> 0 | AB22: =D22+F22+H22+J22+L22+N22+P22+R22+T22+V22+X22+Z22 -> 0 | AC22: =C22+AB22 -> 0
A23: =SOCIOS!A22 -> 21 | B23: =SOCIOS!B22 -> 0 | C23: ='APORTES 2025'!O22 -> 0 | AB23: =D23+F23+H23+J23+L23+N23+P23+R23+T23+V23+X23+Z23 -> 0 | AC23: =C23+AB23 -> 0
A24: =SOCIOS!A23 -> 22 | B24: =SOCIOS!B23 -> 0 | C24: ='APORTES 2025'!O23 -> 0 | AB24: =D24+F24+H24+J24+L24+N24+P24+R24+T24+V24+X24+Z24 -> 0 | AC24: =C24+AB24 -> 0
A25: =SOCIOS!A24 -> 23 | B25: =SOCIOS!B24 -> 0 | C25: ='APORTES 2025'!O24 -> 0 | AB25: =D25+F25+H25+J25+L25+N25+P25+R25+T25+V25+X25+Z25 -> 0 | AC25: =C25+AB25 -> 0
A26: =SOCIOS!A25 -> 24 | B26: =SOCIOS!B25 -> 0 | C26: ='APORTES 2025'!O25 -> 0 | AB26: =D26+F26+H26+J26+L26+N26+P26+R26+T26+V26+X26+Z26 -> 0 | AC26: =C26+AB26 -> 0
A27: =SOCIOS!A26 -> 25 | B27: =SOCIOS!B26 -> 0 | C27: ='APORTES 2025'!O26 -> 0 | AB27: =D27+F27+H27+J27+L27+N27+P27+R27+T27+V27+X27+Z27 -> 0 | AC27: =C27+AB27 -> 0
B28: Ingreso total del mes | D28: =SUM(D3:D27) -> 1500 | E28: =SUM(E3:E27) -> 55 | F28: =SUM(F3:F27) -> 1500 | G28: =SUM(G3:G27) -> 15 | H28: =SUM(H3:H27) -> 1505 | I28: =SUM(I3:I27) -> 15 | J28: =SUM(J3:J27) -> 1500 | K28: =SUM(K3:K27) -> 5 | ... AB28: =SUM(AB3:AB27) -> 10605 | AC28: =SUM(AC3:AC27)+#REF! -> #REF!
D29: =D28+E28 -> 1555 | F29: =F28+G28 -> 1515 | H29: =H28+I28 -> 1520 | J29: =J28+K28 -> 1505 | L29: =L28+M28 -> 1500 | N29: =N28+O28 -> 1520 | P29: =P28+Q28 -> 1605

Sheet APORTES 2025
A1: N° | B1: Socio | C1: ENE | D1: FEB | E1: MAR | F1: ABR | G1: MAY | H1: JUN | I1: JUL | J1: AGO | K1: SEP | L1: OCT | M1: NOV | N1: DIC | O1: Total
A2: =SOCIOS!A2 -> 1 | B2: =SOCIOS!B2 -> Filomena Valdez Curi | C2: 0 | D2: 100 | E2: 100 | F2: 100 | G2: 100 | H2: 100 | I2: 100 | J2: 100 | K2: 100 | L2: 100 | M2: 100 | N2: 100 | O2: =SUM(C2:N2) -> 1100
A3: =SOCIOS!A3 -> 2 | B3: =SOCIOS!B3 -> Efrain Infante Mejia | C3: 0 | D3: 100 | E3: 100 | F3: 100 | G3: 100 | H3: 100 | I3: 100 | J3: 100 | K3: 100 | L3: 100 | M3: 100 | N3: 100 | O3: =SUM(C3:N3) -> 1100
A4: =SOCIOS!A4 -> 3 | B4: =SOCIOS!B4 -> Estefani Corali Infante Fernández | C4: 0 | D4: 100 | E4: 100 | F4: 100 | G4: 100 | H4: 100 | I4: 100 | J4: 100 | K4: 100 | L4: 100 | M4: 100 | N4: 100 | O4: =SUM(C4:N4) -> 1100
A5: =SOCIOS!A5 -> 4 | B5: =SOCIOS!B5 -> Juan Carlos Cuba Sulca | C5: 0 | D5: 100 | E5: 100 | F5: 100 | G5: 100 | H5: 100 | I5: 100 | J5: 100 | K5: 100 | L5: 100 | M5: 100 | N5: 100 | O5: =SUM(C5:N5) -> 1100
A6: =SOCIOS!A6 -> 5 | B6: =SOCIOS!B6 -> Julio Cesar Fernandez Valdez | C6: 0 | D6: 100 | E6: 100 | F6: 100 | G6: 100 | H6: 100 | I6: 100 | J6: 100 | K6: 100 | L6: 100 | M6: 100 | N6: 100 | O6: =SUM(C6:N6) -> 1100
A7: =SOCIOS!A7 -> 6 | B7: =SOCIOS!B7 -> Mariela Fernández Valdez | C7: 0 | D7: 100 | E7: 100 | F7: 100 | G7: 100 | H7: 100 | I7: 100 | J7: 100 | K7: 100 | L7: 100 | M7: 100 | N7: 100 | O7: =SUM(C7:N7) -> 1100
A8: =SOCIOS!A8 -> 7 | B8: =SOCIOS!B8 -> Michael Fernández Valdez | C8: 0 | D8: 100 | E8: 100 | F8: 100 | G8: 100 | H8: 100 | I8: 100 | J8: 100 | K8: 100 | L8: 100 | M8: 100 | N8: 100 | O8: =SUM(C8:N8) -> 1100
A9: =SOCIOS!A9 -> 8 | B9: =SOCIOS!B9 -> Paul Jimmy Auccapuclla Barrientos | C9: 0 | D9: 100 | E9: 100 | F9: 100 | G9: 100 | H9: 100 | I9: 100 | J9: 100 | K9: 100 | L9: 100 | M9: 100 | N9: 100 | O9: =SUM(C9:N9) -> 1100
A10: =SOCIOS!A10 -> 9 | B10: =SOCIOS!B10 -> Saul Godoy Mallqui | C10: 0 | D10: 100 | E10: 100 | F10: 100 | G10: 100 | H10: 100 | I10: 100 | J10: 100 | K10: 100 | L10: 100 | M10: 100 | N10: 100 | O10: =SUM(C10:N10) -> 1100
A11: =SOCIOS!A11 -> 10 | B11: =SOCIOS!B11 -> Sayda Quispe Curi | C11: 0 | D11: 100 | E11: 100 | F11: 100 | G11: 100 | H11: 100 | I11: 100 | J11: 100 | K11: 100 | L11: 100 | M11: 100 | N11: 100 | O11: =SUM(C11:N11) -> 1100
A12: =SOCIOS!A12 -> 11 | B12: =SOCIOS!B12 -> Yeli Melusca Algoner Mejia | C12: 0 | D12: 100 | E12: 100 | F12: 100 | G12: 100 | H12: 100 | I12: 100 | J12: 100 | K12: 100 | L12: 100 | M12: 100 | N12: 100 | O12: =SUM(C12:N12) -> 1100
A13: =SOCIOS!A13 -> 12 | B13: =SOCIOS!B13 -> Yésica Godoy Mallqui | C13: 0 | D13: 100 | E13: 100 | F13: 100 | G13: 100 | H13: 100 | I13: 100 | J13: 100 | K13: 100 | L13: 100 | M13: 100 | N13: 100 | O13: =SUM(C13:N13) -> 1100
... A26: =SOCIOS!A26 -> 25 | B26: =SOCIOS!B26 -> 0 | C26: 0 | D26: 0 | E26: 0 | F26: 0 | G26: 0 | H26: 0 | I26: 0 | J26: 0 | K26: 0 | L26: 0 | M26: 0 | N26: 0 | O26: =SUM(C26:N26) -> 0
C27: =SUM(C2:C26) -> 0 | D27: =SUM(D2:D26) -> 1200 | E27: =SUM(E2:E26) -> 1200 | F27: =SUM(F2:F26) -> 1200 | G27: =SUM(G2:G26) -> 1200 | H27: =SUM(H2:H26) -> 1200 | I27: =SUM(I2:I26) -> 1200 | J27: =SUM(J2:J26) -> 1200 | ... N27: =SUM(N2:N26) -> 1200

Sheet REUNIONES
A2: N° | B2: SOCIO | C2: REUNION | D2: 46167
A3: =SOCIOS!A2 -> 1 | B3: =SOCIOS!B2 -> Filomena Valdez Curi | C3: 1 | D3: 0
A4: =SOCIOS!A3 -> 2 | B4: =SOCIOS!B3 -> Efrain Infante Mejia | D4: 1
A5: =SOCIOS!A4 -> 3 | B5: =SOCIOS!B4 -> Estefani Corali Infante Fernández | D5: 0
A6: =SOCIOS!A5 -> 4 | B6: =SOCIOS!B5 -> Juan Carlos Cuba Sulca | D6: 1
A7: =SOCIOS!A6 -> 5 | B7: =SOCIOS!B6 -> Julio Cesar Fernandez Valdez | D7: 1
A8: =SOCIOS!A7 -> 6 | B8: =SOCIOS!B7 -> Mariela Fernández Valdez | D8: 1
A9: =SOCIOS!A8 -> 7 | B9: =SOCIOS!B8 -> Michael Fernández Valdez | D9: 0
A10: =SOCIOS!A9 -> 8 | B10: =SOCIOS!B9 -> Paul Jimmy Auccapuclla Barrientos | D10: 1
A11: =SOCIOS!A10 -> 9 | B11: =SOCIOS!B10 -> Saul Godoy Mallqui | D11: 1
A12: =SOCIOS!A11 -> 10 | B12: =SOCIOS!B11 -> Sayda Quispe Curi | D12: 1
A13: =SOCIOS!A12 -> 11 | B13: =SOCIOS!B12 -> Yeli Melusca Algoner Mejia | D13: 1
A14: =SOCIOS!A13 -> 12 | B14: =SOCIOS!B13 -> Yésica Godoy Mallqui | D14: 1
A15: =SOCIOS!A14 -> 13 | B15: =SOCIOS!B14 -> Maribel Cayllahua Sulcacondor | D15: 0
... A17: =SOCIOS!A16 -> 15 | B17: =SOCIOS!B16 -> Brith Zarella Roca Godoy | D17: 1
A18: =SOCIOS!A17 -> 16 | B18: =SOCIOS!B17 -> Jeferson Mendoza Quispe
A19: =SOCIOS!A18 -> 17 | B19: =SOCIOS!B18 -> 0
A20: =SOCIOS!A19 -> 18 | B20: =SOCIOS!B19 -> 0
A21: =SOCIOS!A20 -> 19 | B21: =SOCIOS!B20 -> 0
A22: =SOCIOS!A21 -> 20 | B22: =SOCIOS!B21 -> 0
A23: =SOCIOS!A22 -> 21 | B23: =SOCIOS!B22 -> 0
A24: =SOCIOS!A23 -> 22 | B24: =SOCIOS!B23 -> 0
A25: =SOCIOS!A24 -> 23 | B25: =SOCIOS!B24 -> 0
D26: =SUM(D3:D25) -> 11
